mkdocs_awesome_nav/__init__.py
mkdocs_awesome_nav/log.py
mkdocs_awesome_nav/plugin.py
mkdocs_awesome_nav/utils.py
mkdocs_awesome_nav/nav/__init__.py
mkdocs_awesome_nav/nav/config.py
mkdocs_awesome_nav/nav/context.py
mkdocs_awesome_nav/nav/directory.py
mkdocs_awesome_nav/nav/link.py
mkdocs_awesome_nav/nav/page.py
mkdocs_awesome_nav/nav/pattern.py
mkdocs_awesome_nav/nav/resolve.py
mkdocs_awesome_nav/nav/section.py
mkdocs_awesome_nav-3.1.2.dist-info/entry_points.txt
mkdocs_awesome_nav-3.1.2.dist-info/licenses/LICENSE.md
mkdocs_awesome_nav-3.1.2.dist-info/WHEEL
mkdocs_awesome_nav-3.1.2.dist-info/METADATA
mkdocs_awesome_nav-3.1.2.dist-info/RECORD
