Metadata-Version: 2.4
Name: mkdocs-awesome-nav
Version: 3.1.2
Summary: A plugin for customizing the navigation structure of your MkDocs site.
Keywords: mkdocs,markdown,documentation,navigation
Author-email: Lukas Geiter <info@lukasgeiter.com>
Requires-Python: >=3.10
Classifier: License :: OSI Approved :: MIT License
Classifier: Development Status :: 5 - Production/Stable
Classifier: Intended Audience :: Developers
Classifier: Intended Audience :: Information Technology
License-File: LICENSE.md
Requires-Dist: mkdocs>=1.6.0
Requires-Dist: natsort>=8.1.0
Requires-Dist: pydantic>=2.0.2; python_version<'3.13'
Requires-Dist: pydantic>=2.8.1; python_version>='3.13'
Requires-Dist: wcmatch>=8.4
Project-URL: source, https://github.com/lukasgeiter/mkdocs-awesome-nav/
